streamlit_d3_network_component/__init__.py
streamlit_d3_network_component/frontend/build/asset-manifest.json
streamlit_d3_network_component/frontend/build/favicon.ico
streamlit_d3_network_component/frontend/build/index.html
streamlit_d3_network_component/frontend/build/logo192.png
streamlit_d3_network_component/frontend/build/logo512.png
streamlit_d3_network_component/frontend/build/manifest.json
streamlit_d3_network_component/frontend/build/precache-manifest.4746b0266f22c1d7ff3f6ae6ca9e9f8b.js
streamlit_d3_network_component/frontend/build/precache-manifest.ddc3f750a3a7b44466b0d376572f7efd.js
streamlit_d3_network_component/frontend/build/robots.txt
streamlit_d3_network_component/frontend/build/service-worker.js
streamlit_d3_network_component/frontend/build/static/css/2.0d21f304.chunk.css
streamlit_d3_network_component/frontend/build/static/css/2.0d21f304.chunk.css.map
streamlit_d3_network_component/frontend/build/static/css/main.c3e5bb93.chunk.css
streamlit_d3_network_component/frontend/build/static/css/main.c3e5bb93.chunk.css.map
streamlit_d3_network_component/frontend/build/static/js/2.0a9d1d3f.chunk.js
streamlit_d3_network_component/frontend/build/static/js/2.0a9d1d3f.chunk.js.LICENSE.txt
streamlit_d3_network_component/frontend/build/static/js/2.0a9d1d3f.chunk.js.map
streamlit_d3_network_component/frontend/build/static/js/2.e9368623.chunk.js
streamlit_d3_network_component/frontend/build/static/js/2.e9368623.chunk.js.LICENSE.txt
streamlit_d3_network_component/frontend/build/static/js/2.e9368623.chunk.js.map
streamlit_d3_network_component/frontend/build/static/js/main.0cb52d20.chunk.js
streamlit_d3_network_component/frontend/build/static/js/main.0cb52d20.chunk.js.map
streamlit_d3_network_component/frontend/build/static/js/main.e1d1cd7b.chunk.js
streamlit_d3_network_component/frontend/build/static/js/main.e1d1cd7b.chunk.js.map
streamlit_d3_network_component/frontend/build/static/js/runtime-main.18a1b64b.js
streamlit_d3_network_component-0.0.10.dist-info/METADATA
streamlit_d3_network_component-0.0.10.dist-info/WHEEL
streamlit_d3_network_component-0.0.10.dist-info/top_level.txt
streamlit_d3_network_component-0.0.10.dist-info/RECORD
